fastmask/__init__.py
fastmask/cli.py
fastmask/config.py
fastmask/masked_email.py
fastmask/utils.py
fastmask/version.py
fastmask-0.1.6.dist-info/METADATA
fastmask-0.1.6.dist-info/WHEEL
fastmask-0.1.6.dist-info/entry_points.txt
fastmask-0.1.6.dist-info/top_level.txt
fastmask-0.1.6.dist-info/RECORD
