Metadata-Version: 2.1
Name: fastmask
Version: 0.1.6
Summary: Python library + CLI for Fastmail masked email
Home-page: https://github.com/hdb/fastmask
Author: Hudson Bailey
Author-email: dev@hudsonbailey.org
License: MIT
Requires-Dist: Click
Requires-Dist: requests
Requires-Dist: python-dotenv
Requires-Dist: rich
Requires-Dist: pandas
